DeepSR/DeepSR.py
DeepSR/LossHistory.py
DeepSR/__init__.py
DeepSR/args.py
DeepSR/epoch_sleep.py
DeepSR/template.txt
DeepSR/utils.py
DeepSR/docs/DeepSR Manual.pdf
DeepSR/docs/Implementation.png
DeepSR/docs/The DeepSR.png
DeepSR/docs/Training.png
DeepSR/docs/conceptual scheme.png
"DeepSR/samples/DIV2K, All Results.xlsx"
"DeepSR/samples/DIV2K, Best Scores, unstacked.xlsx"
"DeepSR/samples/DIV2K, Best Scores.xlsx"
DeepSR/samples/DiV2K_Run_on_Excel.py
DeepSR/samples/EDSR_RGB.py
DeepSR/samples/README.md
DeepSR/samples/SRCNN.py
DeepSR/samples/SRCNN_2.py
"DeepSR/samples/Set14, Adapted Best Scores.xlsx"
"DeepSR/samples/Set5, Adapted Best Scores.xlsx"
DeepSR/samples/VDSR.py
DeepSR/samples/VGG-19.py
DeepSR/samples/_All together.xlsx
DeepSR/samples/karistir.py
DeepSR/samples/sample_1.ipynb
DeepSR/samples/sample_for_using_DeepSR_as_class_object.py
DeepSR/samples/sample_model_1.py
DeepSR/samples/sample_model_2.py
"DeepSR/samples/set14, All Results.xlsx"
"DeepSR/samples/set14, Best Scores, unstacked.xlsx"
"DeepSR/samples/set14, Best Scores.xlsx"
"DeepSR/samples/set5, All Results.xlsx"
"DeepSR/samples/set5, Best Scores, unstacked.xlsx"
"DeepSR/samples/set5, Best Scores.xlsx"
DeepSR/samples/write_scripts.py
DeepSR-0.0.120.dist-info/METADATA
DeepSR-0.0.120.dist-info/WHEEL
DeepSR-0.0.120.dist-info/license.txt
DeepSR-0.0.120.dist-info/top_level.txt
DeepSR-0.0.120.dist-info/RECORD
