Metadata-Version: 2.1
Name: DeepSR
Version: 0.0.120
Summary: A Toolkit for Super Resolution with Deep Learning Algorithms
Home-page: https://github.com/htemiz/DeepSR
Author: Hakan Temiz
Author-email: htemiz@artvin.edu.tr
License: UNKNOWN
Project-URL: Documentation, https://github.com/htemiz/deepsr/tree/master/DeepSR/docs
Project-URL: Source, https://github.com/htemiz/deepsr/tree/master/DeepSR
Keywords: super resolution deep learning DeepSR
Platform: UNKNOWN
Classifier: Programming Language :: Python :: 3
Classifier: License :: OSI Approved :: MIT License
Classifier: Operating System :: OS Independent
Requires-Python: >=3
License-File: license.txt
Requires-Dist: scipy >=1.4.1
Requires-Dist: pandas
Requires-Dist: h5py
Requires-Dist: matplotlib
Requires-Dist: scikit-image >=0.17.2
Requires-Dist: scikit-video >=1.1.11
Requires-Dist: sporco >=0.2.0
Requires-Dist: Pillow
Requires-Dist: sewar >=0.4.3
Requires-Dist: openpyxl
Requires-Dist: numpy >=1.15.0
Requires-Dist: tensorflow >=2.0.0
Requires-Dist: theano
Requires-Dist: keras >=2.0.0
Requires-Dist: setuptools >41.0.0
Requires-Dist: markdown >=2.2.0
Requires-Dist: GraphViz
Requires-Dist: pyfftw >=0.12.0
